README.rst
setup.cfg
setup.py
pyopossum3/__init__.py
pyopossum3.egg-info/PKG-INFO
pyopossum3.egg-info/SOURCES.txt
pyopossum3.egg-info/dependency_links.txt
pyopossum3.egg-info/requires.txt
pyopossum3.egg-info/top_level.txt
pyopossum3.egg-info/zip-safe