Metadata-Version: 1.1
Name: pyopossum3
Version: 0.1
Summary: SQLAlchemy-based interface to the oPOSSUM3 transcription factor binding database.
Home-page: https://github.com/konstantint/pyopossum3
Author: Konstantin Tretyakov
Author-email: kt@ut.ee
License: MIT
Keywords: bioinformatics oPOSSUM3 data-access transcription tfbs
Platform: Platform Independent
Classifier: Development Status :: 3 - Alpha
Classifier: Intended Audience :: Science/Research
Classifier: License :: OSI Approved :: MIT License
Classifier: Operating System :: OS Independent
Classifier: Programming Language :: Python :: 2
Classifier: Topic :: Scientific/Engineering :: Bio-Informatics
